HISTORY.rst
LICENSE
MANIFEST.in
README.rst
flask_xstatic.py
setup.py
Flask_XStatic.egg-info/PKG-INFO
Flask_XStatic.egg-info/SOURCES.txt
Flask_XStatic.egg-info/dependency_links.txt
Flask_XStatic.egg-info/not-zip-safe
Flask_XStatic.egg-info/requires.txt
Flask_XStatic.egg-info/top_level.txt