Metadata-Version: 1.1
Name: Flask-XStatic
Version: 0.0.1
Summary: Flask support for XStatic assets
Home-page: https://github.com/emillon/flask-xstatic
Author: Etienne Millon
Author-email: me@emillon.org
License: BSD
Platform: UNKNOWN
Classifier: Development Status :: 3 - Alpha
Classifier: Intended Audience :: Developers
Classifier: License :: OSI Approved :: BSD License
Classifier: Operating System :: OS Independent
Classifier: Programming Language :: Python :: 2.6
Classifier: Programming Language :: Python :: 2.7
Classifier: Programming Language :: Python :: 3.3
Classifier: Topic :: Internet :: WWW/HTTP
